pyutilib/__init__.py
pyutilib/autotest/__init__.py
pyutilib/autotest/default_testdriver.py
pyutilib/autotest/driver.py
pyutilib/autotest/json_plugin.py
pyutilib/autotest/plugins.py
pyutilib/autotest/yaml_plugin.py
pyutilib/autotest/tests/__init__.py
pyutilib/autotest/tests/test_driver.py
pyutilib/common/__init__.py
pyutilib/common/_exceptions.py
pyutilib/component/__init__.py
pyutilib/component/app/__init__.py
pyutilib/component/app/simple.py
pyutilib/component/app/tests/__init__.py
pyutilib/component/app/tests/app1a.py
pyutilib/component/app/tests/app1b.py
pyutilib/component/app/tests/app2.py
pyutilib/component/app/tests/app3.py
pyutilib/component/app/tests/app4.py
pyutilib/component/app/tests/test_simple.py
pyutilib/component/config/__init__.py
pyutilib/component/config/configuration.py
pyutilib/component/config/env_config.py
pyutilib/component/config/logging_config.py
pyutilib/component/config/managed_plugin.py
pyutilib/component/config/options.py
pyutilib/component/config/plugin_ConfigParser.py
pyutilib/component/config/tempfiles.py
pyutilib/component/config/tests/__init__.py
pyutilib/component/config/tests/test_config.py
pyutilib/component/config/tests/test_options.py
pyutilib/component/config/tests/test_tempdir.py
pyutilib/component/core/__init__.py
pyutilib/component/core/core.py
pyutilib/component/core/tests/__init__.py
pyutilib/component/core/tests/test_core.py
pyutilib/component/executables/__init__.py
pyutilib/component/executables/executable.py
pyutilib/component/loader/__init__.py
pyutilib/component/loader/plugin_eggLoader.py
pyutilib/component/loader/plugin_importLoader.py
pyutilib/component/loader/tests/__init__.py
pyutilib/component/loader/tests/egg1.py
pyutilib/component/loader/tests/egg2.py
pyutilib/component/loader/tests/load1.py
pyutilib/component/loader/tests/load1a.py
pyutilib/component/loader/tests/load2.py
pyutilib/component/loader/tests/load2a.py
pyutilib/component/loader/tests/test_egg.py
pyutilib/component/loader/tests/test_load.py
PyUtilib-5.8.0.dist-info/AUTHORS.txt
PyUtilib-5.8.0.dist-info/LICENSE.txt
PyUtilib-5.8.0.dist-info/METADATA
PyUtilib-5.8.0.dist-info/WHEEL
PyUtilib-5.8.0.dist-info/entry_points.txt
PyUtilib-5.8.0.dist-info/top_level.txt
PyUtilib-5.8.0.dist-info/RECORD
